tgtk/__init__.py
tgtk/__main__.py
tgtk/ttk_client.py
tgtk/consts/DefaultCommands.py
tgtk/consts/ExecVarsSample.py
tgtk/consts/__init__.py
tgtk/core/HandleManager.py
tgtk/core/__init__.py
tgtk/core/database_handle.py
tgtk/core/getCommand.py
tgtk/core/getVars.py
tgtk/core/nodes.py
tgtk/core/settings.py
tgtk/core/speedtest.py
tgtk/core/thumb_manage.py
tgtk/core/ttk_ytdl.py
tgtk/core/user_settings.py
tgtk/core/varholdern.py
tgtk/core/wserver.py
tgtk/core/status/__init__.py
tgtk/core/status/auto_delete.py
tgtk/core/status/menu.py
tgtk/core/status/status.py
tgtk/core/status/upload.py
tgtk/functions/Ftele.py
tgtk/functions/Hash_Fetch.py
tgtk/functions/Human_Format.py
tgtk/functions/Leech_Module.py
tgtk/functions/QBittorrentWrap.py
tgtk/functions/__init__.py
tgtk/functions/admin_check.py
tgtk/functions/ariatools.py
tgtk/functions/dl_generator.py
tgtk/functions/instadl.py
tgtk/functions/pg_plugin.py
tgtk/functions/progress_for_pyrogram.py
tgtk/functions/progress_for_telethon.py
tgtk/functions/rclone_upload.py
tgtk/functions/tele_upload.py
tgtk/functions/vids_helpers.py
tgtk/functions/zip7_utils.py
tgtk-1.2.3.data/scripts/start.sh
tgtk-1.2.3.dist-info/LICENSE
tgtk-1.2.3.dist-info/METADATA
tgtk-1.2.3.dist-info/WHEEL
tgtk-1.2.3.dist-info/top_level.txt
tgtk-1.2.3.dist-info/RECORD
