Metadata-Version: 2.1
Name: tgtk
Version: 1.2.3
Summary: A Telegram Bot written in Python to mirror files on the internet onto Telegram
Home-page: https://github.com/reaitten/tgtk
Author: reaitten
License: UNKNOWN
Project-URL: Bug Tracker, https://github.com/reaitten/tgtk/issues
Platform: UNKNOWN
Classifier: Programming Language :: Python :: 3
Classifier: License :: OSI Approved :: GNU General Public License v3 (GPLv3)
Classifier: Operating System :: POSIX :: Linux
Classifier: Development Status :: 5 - Production/Stable
Requires-Python: >=3.8
License-File: LICENSE
Requires-Dist: aiohttp (==3.7.4)
Requires-Dist: anytree (==2.8.0)
Requires-Dist: aria2p (==0.9.1)
Requires-Dist: async-timeout (==3.0.1)
Requires-Dist: attrdict (==2.0.1)
Requires-Dist: attrs (==19.3.0)
Requires-Dist: certifi (==2020.6.20)
Requires-Dist: cffi (==1.14.1)
Requires-Dist: chardet (==3.0.4)
Requires-Dist: cryptg (==0.2.post2)
Requires-Dist: gunicorn (==20.0.4)
Requires-Dist: hachoir (==3.1.1)
Requires-Dist: idna (==2.10)
Requires-Dist: multidict (==4.7.6)
Requires-Dist: orjson (==3.3.1)
Requires-Dist: Pillow (==8.1.1)
Requires-Dist: psutil (==5.8.0)
Requires-Dist: psycopg2-binary (==2.8.5)
Requires-Dist: pyaes (==1.6.1)
Requires-Dist: pyasn1 (==0.4.8)
Requires-Dist: pycparser (==2.20)
Requires-Dist: qbittorrent-api (==2020.7.7)
Requires-Dist: requests (==2.24.0)
Requires-Dist: rsa (==4.6)
Requires-Dist: six (==1.15.0)
Requires-Dist: Telethon (==1.20)
Requires-Dist: TgCrypto (==1.2.2)
Requires-Dist: torrentool (==1.1.0)
Requires-Dist: urllib3 (==1.25.10)
Requires-Dist: yarl (==1.5.1)
Requires-Dist: youtube-dl
Requires-Dist: instaloader (==4.6)
Requires-Dist: natsort (==7.1.0)
Requires-Dist: Pyrogram (==1.1.13)
Requires-Dist: beautifulsoup4 (<4.8.10,>=4.8.2)
Requires-Dist: speedtest-cli
Requires-Dist: lxml
